amaascore/__init__.py
amaascore/config.py
amaascore/error_messages.py
amaascore/exceptions.py
amaascore/asset_managers/__init__.py
amaascore/asset_managers/asset_manager.py
amaascore/asset_managers/domain.py
amaascore/asset_managers/enums.py
amaascore/asset_managers/interface.py
amaascore/asset_managers/relationship.py
amaascore/asset_managers/utils.py
amaascore/assets/__init__.py
amaascore/assets/asset.py
amaascore/assets/automobile.py
amaascore/assets/bond.py
amaascore/assets/bond_future.py
amaascore/assets/bond_future_option.py
amaascore/assets/bond_option.py
amaascore/assets/cfd.py
amaascore/assets/children.py
amaascore/assets/commodity_future.py
amaascore/assets/cryptocurrency.py
amaascore/assets/currency.py
amaascore/assets/custom_asset.py
amaascore/assets/derivative.py
amaascore/assets/energy_future.py
amaascore/assets/enums.py
amaascore/assets/equity.py
amaascore/assets/equity_future.py
amaascore/assets/etf.py
amaascore/assets/foreign_exchange.py
amaascore/assets/fund.py
amaascore/assets/future.py
amaascore/assets/future_option.py
amaascore/assets/fx_future.py
amaascore/assets/fx_option.py
amaascore/assets/index.py
amaascore/assets/index_future.py
amaascore/assets/interest_rate_future.py
amaascore/assets/interface.py
amaascore/assets/listed_cfd.py
amaascore/assets/listed_derivative.py
amaascore/assets/option_mixin.py
amaascore/assets/ownership_mixin.py
amaascore/assets/private_investment.py
amaascore/assets/real_asset.py
amaascore/assets/real_estate.py
amaascore/assets/sukuk.py
amaascore/assets/synthetic.py
amaascore/assets/synthetic_from_book.py
amaascore/assets/synthetic_multi_leg.py
amaascore/assets/utils.py
amaascore/assets/warrants.py
amaascore/assets/wine.py
amaascore/books/__init__.py
amaascore/books/book.py
amaascore/books/enums.py
amaascore/books/interface.py
amaascore/books/portfolio.py
amaascore/books/utils.py
amaascore/core/__init__.py
amaascore/core/amaas_model.py
amaascore/core/comment.py
amaascore/core/interface.py
amaascore/core/reference.py
amaascore-0.9.6.dist-info/LICENSE
amaascore-0.9.6.dist-info/METADATA
amaascore-0.9.6.dist-info/WHEEL
amaascore-0.9.6.dist-info/top_level.txt
amaascore-0.9.6.dist-info/RECORD
