Metadata-Version: 2.1
Name: amaascore
Version: 0.9.6
Summary: Asset Management as a Service - Core SDK
Home-page: https://github.com/amaas-fintech/amaas-core-sdk-python
Author: AMaaS
Author-email: tech@amaas.com
License: Apache License 2.0
Platform: UNKNOWN
Classifier: Programming Language :: Python :: 2
Classifier: Programming Language :: Python :: 2.7
Classifier: Programming Language :: Python :: 3
Classifier: Programming Language :: Python :: 3.3
Classifier: Programming Language :: Python :: 3.4
Classifier: Programming Language :: Python :: 3.5
Classifier: Programming Language :: Python :: 3.6
Classifier: Programming Language :: Python :: 3.7
Classifier: Programming Language :: Python :: 3.8
Requires-Dist: amaasutils
Requires-Dist: configparser
Requires-Dist: python-dateutil
Requires-Dist: pytz
Requires-Dist: requests
Requires-Dist: warrant
